pyship/__init__.py
pyship/__main__.py
pyship/_version_.py
pyship/app_info.py
pyship/arguments.py
pyship/atomic_zip.py
pyship/clip.py
pyship/cloud.py
pyship/constants.py
pyship/create_launcher.py
pyship/download.py
pyship/get-pip.py
pyship/logging.py
pyship/main.py
pyship/nsis.py
pyship/py.typed
pyship/pyship.ico
pyship/pyship.py
pyship/pyship_custom_print.py
pyship/pyship_exceptions.py
pyship/pyship_get_icon.py
pyship/pyship_path.py
pyship/pyship_subprocess.py
pyship/launcher/__init__.py
pyship/launcher/__main__.py
pyship/launcher/hash.py
pyship/launcher/launcher.py
pyship/launcher/metadata.py
pyship/launcher/restart_monitor.py
pyship/patch/__init__.py
pyship/patch/pyship_patch.py
pyship-0.1.7.dist-info/LICENSE
pyship-0.1.7.dist-info/METADATA
pyship-0.1.7.dist-info/WHEEL
pyship-0.1.7.dist-info/top_level.txt
pyship-0.1.7.dist-info/RECORD
