Metadata-Version: 2.1
Name: pyship
Version: 0.1.7
Summary: freezer, installer and updater for Python applications
Home-page: https://github.com/jamesabel/pyship
Download-URL: https://github.com/jamesabel/pyship
Author: abel
Author-email: j@abel.co
License: MIT License
Keywords: freezer,installer,ship
License-File: LICENSE
Requires-Dist: setuptools
Requires-Dist: wheel
Requires-Dist: ismain
Requires-Dist: balsa
Requires-Dist: requests
Requires-Dist: attrs
Requires-Dist: typeguard
Requires-Dist: toml
Requires-Dist: pyinstaller
Requires-Dist: semver
Requires-Dist: python-dateutil
Requires-Dist: wheel-inspect
Requires-Dist: boto3
Requires-Dist: awsimple
Requires-Dist: pyshipupdate
